pkutils.py
pkutils-3.0.2.dist-info/LICENSE
pkutils-3.0.2.dist-info/METADATA
pkutils-3.0.2.dist-info/WHEEL
pkutils-3.0.2.dist-info/top_level.txt
pkutils-3.0.2.dist-info/RECORD
